[
  {"title": null, "id": 301, "tags": null, "videoUrl": "9PscUh9670E"},
  {"title": null, "id": 302, "tags": null, "videoUrl": "svP_2e9nDlI"},
  {"title": null, "id": 303, "tags": null, "videoUrl": "CZpG4O0BXW4"},
  {"title": null, "id": 304, "tags": null, "videoUrl": "raMS_WchGlw"},
  {"title": null, "id": 305, "tags": null, "videoUrl": "BimDh040KrA"},
  {"title": null, "id": 306, "tags": null, "videoUrl": "EEWBq2TS9S0"},
  {"title": null, "id": 307, "tags": null, "videoUrl": "v9d-wLNhh4g"},
  {"title": null, "id": 308, "tags": null, "videoUrl": "L3diZ3G6xkE"},
  {"title": null, "id": 309, "tags": null, "videoUrl": "jH4Pac9nUIw"},
  {"title": null, "id": 310, "tags": null, "videoUrl": "icZ40tDzRMA"},
  {"title": null, "id": 311, "tags": null, "videoUrl": "hS3M4O4v2ic"},
  {"title": null, "id": 312, "tags": null, "videoUrl": "44RXuYhRxsA"},
  {"title": null, "id": 313, "tags": null, "videoUrl": "XiHRIJhxoVg"},
  {"title": null, "id": 314, "tags": null, "videoUrl": "4oYIXh4nEe8"},
  {"title": null, "id": 315, "tags": null, "videoUrl": "Y9ibTUXb4W8"},
  {"title": null, "id": 316, "tags": null, "videoUrl": "wMTGaDZXsAE"},
  {"title": null, "id": 317, "tags": null, "videoUrl": "3mhQ5lRILxM"},
  {"title": null, "id": 318, "tags": null, "videoUrl": "3BZzTc3Da9c"},
  {"title": null, "id": 319, "tags": null, "videoUrl": "9B-NfLc7Ndo"},
  {"title": null, "id": 320, "tags": null, "videoUrl": "URZmA_xKxzw"},
  {"title": null, "id": 321, "tags": null, "videoUrl": "u6I8U72cM3o"},
  {"title": null, "id": 322, "tags": null, "videoUrl": "7DipSBEnP-U"},
  {"title": null, "id": 323, "tags": null, "videoUrl": "lrLrzY2EYzU"},
  {"title": null, "id": 324, "tags": null, "videoUrl": "VEIUj6Hph9c"},
  {"title": null, "id": 325, "tags": null, "videoUrl": "s0Wb50c4oEQ"},
  {"title": null, "id": 326, "tags": null, "videoUrl": "05PUmHsw2Qo"},
  {"title": null, "id": 327, "tags": null, "videoUrl": "t9Xv2nr_pr4"},
  {"title": null, "id": 328, "tags": null, "videoUrl": "nqjFjs_u1t4"},
  {"title": null, "id": 329, "tags": null, "videoUrl": "jg59bB0Ud-g"},
  {"title": null, "id": 330, "tags": null, "videoUrl": "wNjzPg0s9jw"},
  {"title": null, "id": 331, "tags": null, "videoUrl": "_8P7qft_MfE"},
  {"title": null, "id": 332, "tags": null, "videoUrl": "P-599AQzWqU"},
  {"title": null, "id": 333, "tags": null, "videoUrl": "g2ePTLcjWN4"},
  {"title": null, "id": 334, "tags": null, "videoUrl": "EOnopbmnyv8"},
  {"title": null, "id": 335, "tags": null, "videoUrl": "kCREuRQDzIA"},
  {"title": null, "id": 336, "tags": null, "videoUrl": "xgboT2WP7j4"},
  {"title": null, "id": 337, "tags": null, "videoUrl": "SccjxndtBOw"},
  {"title": null, "id": 338, "tags": null, "videoUrl": "svHf8fDHRHo"},
  {"title": null, "id": 339, "tags": null, "videoUrl": "8z6LMKRmNgE"},
  {"title": null, "id": 340, "tags": null, "videoUrl": "eUkOU2HT_Mk"},
  {"title": null, "id": 341, "tags": null, "videoUrl": "voOX9rPpCd4"},
  {"title": null, "id": 342, "tags": null, "videoUrl": "40JBWx98lJc"},
  {"title": null, "id": 343, "tags": null, "videoUrl": "uZvsfmvFMf4"},
  {"title": null, "id": 344, "tags": null, "videoUrl": "D4BY1LyVz7c"},
  {"title": null, "id": 345, "tags": null, "videoUrl": "DwSWSL31-2o"},
  {"title": null, "id": 346, "tags": null, "videoUrl": "3fjwKrgbUk8"},
  {"title": null, "id": 347, "tags": null, "videoUrl": "YcbWJLSaH5I"},
  {"title": null, "id": 348, "tags": null, "videoUrl": "VGT9L7PYk3Q"},
  {"title": null, "id": 349, "tags": null, "videoUrl": "s7iwYwmp7jk"},
  {"title": null, "id": 350, "tags": null, "videoUrl": "VGWZQNTamMY"},
  {"title": null, "id": 351, "tags": null, "videoUrl": "Mv74JsCIH48"},
  {"title": null, "id": 352, "tags": null, "videoUrl": "RoyMIexRW0U"},
  {"title": null, "id": 353, "tags": null, "videoUrl": "f2x2vDaabsg"},
  {"title": null, "id": 354, "tags": null, "videoUrl": "g-wjK89brik"},
  {"title": null, "id": 355, "tags": null, "videoUrl": "umKPl1O3Vqg"},
  {"title": null, "id": 356, "tags": null, "videoUrl": "6b5Nxa4-DJk"},
  {"title": null, "id": 357, "tags": null, "videoUrl": "J65ri-YAA6E"},
  {"title": null, "id": 358, "tags": null, "videoUrl": "rrM7ukzSA_4"},
  {"title": null, "id": 359, "tags": null, "videoUrl": "p_7A3PbSUOw"},
  {"title": null, "id": 360, "tags": null, "videoUrl": "y4W5f6H-V_0"},
  {"title": null, "id": 361, "tags": null, "videoUrl": "TlORxXv__Os"}
]
